offstream/__init__.py
offstream/__main__.py
offstream/app.py
offstream/cli.py
offstream/db.py
offstream/static/favicon.ico
offstream/static/robots.txt
offstream/streaming/__init__.py
offstream/streaming/hls.py
offstream/streaming/recorder.py
offstream/templates/rss.xml
offstream/templates/welcome.html
offstream-1.0.3.dist-info/LICENSE
offstream-1.0.3.dist-info/METADATA
offstream-1.0.3.dist-info/WHEEL
offstream-1.0.3.dist-info/entry_points.txt
offstream-1.0.3.dist-info/top_level.txt
offstream-1.0.3.dist-info/RECORD
