Metadata-Version: 2.1
Name: offstream
Version: 1.0.3
Summary: Personal twitch stream recorder
Home-page: https://github.com/soylent/offstream
Author: soylent
Author-email: 
Keywords: twitch,streaming
Classifier: Development Status :: 5 - Production/Stable
Classifier: Environment :: Console
Classifier: Intended Audience :: End Users/Desktop
Classifier: License :: OSI Approved :: MIT License
Classifier: Operating System :: OS Independent
Classifier: Programming Language :: Python :: 3
Classifier: Programming Language :: Python :: 3.8
Classifier: Programming Language :: Python :: 3.9
Classifier: Programming Language :: Python :: 3.10
Classifier: Topic :: Games/Entertainment
Classifier: Topic :: Multimedia :: Video
Requires-Python: >=3.8
License-File: LICENSE
Requires-Dist: flask (~=2.0)
Requires-Dist: ipfshttpclient (~=0.8.0a2)
Requires-Dist: sqlalchemy (~=1.4)
Requires-Dist: streamlink (~=3.1.1)
Provides-Extra: test
Requires-Dist: pytest (~=6.2) ; extra == 'test'
Requires-Dist: pytest-cov (~=3.0) ; extra == 'test'
Requires-Dist: python-dotenv (~=0.19) ; extra == 'test'
Requires-Dist: types-requests (~=2.26) ; extra == 'test'
Requires-Dist: sqlalchemy[mypy] (~=1.4) ; extra == 'test'
